uk_covid19/__init__.py
uk_covid19/api_interface.py
uk_covid19/data_format.py
uk_covid19/exceptions.py
uk_covid19/utils.py
uk_covid19-1.2.2.dist-info/LICENSE
uk_covid19-1.2.2.dist-info/METADATA
uk_covid19-1.2.2.dist-info/WHEEL
uk_covid19-1.2.2.dist-info/top_level.txt
uk_covid19-1.2.2.dist-info/RECORD
