Metadata-Version: 2.1
Name: uk-covid19
Version: 1.2.2
Summary: SDK for the COVID-19 API (Coronavirus Dashboard in the UK)
Home-page: https://coronavirus.data.gov.uk/
Author: Pouria Hadjibagheri
Author-email: Pouria.Hadjibagheri@phe.gov.uk
Maintainer: Public Health England - Coronavirus Dashboard Team
Maintainer-email: covid19-tech@phe.gov.uk
License: MIT
Keywords: API SDK PHE COVID19 COVID-19 coronavirus data UK England Wales Scotland Northern_Ireland United_Kingdom
Platform: UNKNOWN
Classifier: Development Status :: 5 - Production/Stable
Classifier: Environment :: Console
Classifier: Intended Audience :: Developers
Classifier: Intended Audience :: Healthcare Industry
Classifier: Intended Audience :: Science/Research
Classifier: License :: OSI Approved :: MIT License
Classifier: Operating System :: OS Independent
Classifier: Programming Language :: Python :: 3.7
Classifier: Programming Language :: Python :: 3.8
Classifier: Topic :: Software Development :: Libraries :: Python Modules
Classifier: Topic :: Software Development
Classifier: Topic :: Database
Classifier: Topic :: Internet :: WWW/HTTP :: Indexing/Search
Classifier: Topic :: Internet :: WWW/HTTP :: Dynamic Content
Requires-Python: >=3.7
